here/__init__.py
here/here.py
here-1.4.0.dist-info/METADATA
here-1.4.0.dist-info/WHEEL
here-1.4.0.dist-info/top_level.txt
here-1.4.0.dist-info/RECORD
