Metadata-Version: 2.4
Name: here
Version: 1.4.0
Summary: Python package that replicates the R package called 'here'.
Author-email: Michael Boerman <michaelboerman@hey.com>
Project-URL: Homepage, https://github.com/michaelboerman/here
Project-URL: Issues, https://github.com/michaelboerman/here/issues
Classifier: Programming Language :: Python :: 3
Classifier: License :: OSI Approved :: MIT License
Classifier: Operating System :: OS Independent
Requires-Python: >=3.8
